pangpuriye/README.md
pangpuriye/ai/ocr.py
pangpuriye/common/file_handler.py
pangpuriye/tests/test_ocr.py
pangpuriye-0.1.8.dist-info/WHEEL
pangpuriye-0.1.8.dist-info/METADATA
pangpuriye-0.1.8.dist-info/RECORD
