Metadata-Version: 2.1
Name: pangpuriye
Version: 0.1.8
Summary: Let's make AI easy.
Home-page: https://github.com/patharanordev/pangpuriye/blob/main/python/pangpuriye/pangpuriye
License: MIT
Author: Pathara Norasethasopon
Author-email: patharanor@gmail.com
Requires-Python: >=3.6,<4.0
Classifier: License :: OSI Approved :: MIT License
Classifier: Programming Language :: Python :: 3
Classifier: Programming Language :: Python :: 3.6
Classifier: Programming Language :: Python :: 3.7
Classifier: Programming Language :: Python :: 3.8
Classifier: Programming Language :: Python :: 3.9
Project-URL: Repository, https://github.com/patharanordev/pangpuriye/blob/main/python/pangpuriye/pangpuriye
